LICENSE
README.md
setup.py
manygame/__init__.py
manygame.egg-info/PKG-INFO
manygame.egg-info/SOURCES.txt
manygame.egg-info/dependency_links.txt
manygame.egg-info/top_level.txt