Metadata-Version: 2.2
Name: manygame
Version: 1.0.0
Summary: manygame是一个有趣的4款命令行小游戏。
Author: huangfeng
Author-email: 
Keywords: python,manygame,windows,mac,linux
Classifier: Development Status :: 4 - Beta
Classifier: Programming Language :: Python :: 3.11
Classifier: Programming Language :: Python :: 3.12
Classifier: Operating System :: OS Independent
Classifier: Development Status :: 4 - Beta
Classifier: Topic :: Games/Entertainment
Classifier: Topic :: Terminals
Classifier: Topic :: Games/Entertainment :: Puzzle Games
Classifier: Topic :: Games/Entertainment :: Turn Based Strategy
Classifier: Intended Audience :: End Users/Desktop
Classifier: Environment :: Console
Classifier: Operating System :: Microsoft :: Windows
Classifier: Environment :: Win32 (MS Windows)
License-File: LICENSE
Dynamic: author
Dynamic: classifier
Dynamic: description
Dynamic: description-content-type
Dynamic: keywords
Dynamic: summary
